cs/binary.py
cs_binary-20250501.dist-info/WHEEL
cs_binary-20250501.dist-info/METADATA
cs_binary-20250501.dist-info/RECORD
