Metadata-Version: 2.4
Name: cs-binary
Version: 20250501
Summary: Facilities associated with binary data parsing and transcription. The classes in this module support easy parsing of binary data structures, returning instances with the binary data decoded into attributes and capable of transcribing themselves in binary form (trivially via `bytes(instance)` and also otherwise).
Keywords: python3
Author-email: Cameron Simpson <cs@cskk.id.au>
Requires-Python: >=3.6
Classifier: Development Status :: 4 - Beta
Classifier: Environment :: Console
Classifier: Programming Language :: Python :: 3
Classifier: Intended Audience :: Developers
Classifier: Operating System :: OS Independent
Classifier: Topic :: Software Development :: Libraries :: Python Modules
Classifier: License :: OSI Approved :: GNU General Public License v3 or later (GPLv3+)
Requires-Dist: cs.buffer>=20250428
Requires-Dist: cs.deco>=20250428
Requires-Dist: cs.gimmicks>=20250428
Requires-Dist: cs.lex>=20250428
Requires-Dist: cs.pfx>=20250308
Requires-Dist: cs.seq>=20250306
Requires-Dist: typeguard
Project-URL: MonoRepo Commits, https://bitbucket.org/cameron_simpson/css/commits/branch/main
Project-URL: Monorepo Git Mirror, https://github.com/cameron-simpson/css
Project-URL: Monorepo Hg/Mercurial Mirror, https://hg.sr.ht/~cameron-simpson/css
Project-URL: Source, https://github.com/cameron-simpson/css/blob/main/lib/python/cs/binary.py
